LICENSE.txt
MANIFEST.in
README.md
setup.cfg
setup.py
p_tqdm/__init__.py
p_tqdm/_version.py
p_tqdm/p_tqdm.py
p_tqdm.egg-info/PKG-INFO
p_tqdm.egg-info/SOURCES.txt
p_tqdm.egg-info/dependency_links.txt
p_tqdm.egg-info/requires.txt
p_tqdm.egg-info/top_level.txt
tests/test_p_tqdm.py