Metadata-Version: 2.1
Name: p_tqdm
Version: 1.4.1
Summary: Parallel processing with progress bars
Home-page: https://github.com/swansonk14/p_tqdm
Download-URL: https://github.com/swansonk14/p_tqdm/v_1.4.1.tar.gz
Author: Kyle Swanson
Author-email: swansonk.14@gmail.com
License: MIT
Keywords: tqdm,progress bar,parallel
Classifier: Programming Language :: Python :: 3
Classifier: Programming Language :: Python :: 3.8
Classifier: Programming Language :: Python :: 3.9
Classifier: Programming Language :: Python :: 3.10
Classifier: Programming Language :: Python :: 3.11
Classifier: Programming Language :: Python :: 3.12
Classifier: License :: OSI Approved :: MIT License
Classifier: Operating System :: OS Independent
License-File: LICENSE.txt
Requires-Dist: tqdm>=4.45.0
Requires-Dist: pathos>=0.2.5
Requires-Dist: six>=1.13.0
